nollama/__init__.py
nollama/nollama.py
nollama-0.4.dist-info/licenses/LICENSE
nollama-0.4.dist-info/METADATA
nollama-0.4.dist-info/WHEEL
nollama-0.4.dist-info/entry_points.txt
nollama-0.4.dist-info/top_level.txt
nollama-0.4.dist-info/RECORD
