Metadata-Version: 2.4
Name: nollama
Version: 0.4
Summary: A terminal-based interface for interacting with large language models (LLMs)
Home-page: https://github.com/spignelon/nollama
Author: Ujjawal Saini
Author-email: spignelon@proton.me
License: GPL-3.0
Classifier: Development Status :: 3 - Alpha
Classifier: Intended Audience :: Developers
Classifier: License :: OSI Approved :: GNU General Public License v3 (GPLv3)
Classifier: Programming Language :: Python :: 3.9
Classifier: Programming Language :: Python :: 3.10
Classifier: Programming Language :: Python :: 3.11
Classifier: Programming Language :: Python :: 3.12
Requires-Python: >=3.9
License-File: LICENSE
Requires-Dist: aiohappyeyeballs==2.6.1
Requires-Dist: aiohttp==3.12.7
Requires-Dist: aiosignal==1.3.2
Requires-Dist: annotated-types==0.7.0
Requires-Dist: anyio==4.9.0
Requires-Dist: attrs==25.3.0
Requires-Dist: blessed==1.21.0
Requires-Dist: cachetools==5.5.2
Requires-Dist: certifi==2025.4.26
Requires-Dist: charset-normalizer==3.4.2
Requires-Dist: editor==1.6.6
Requires-Dist: frozenlist==1.6.2
Requires-Dist: google-auth==2.40.2
Requires-Dist: google-genai==1.18.0
Requires-Dist: h11==0.16.0
Requires-Dist: httpcore==1.0.9
Requires-Dist: httpx==0.28.1
Requires-Dist: idna==3.10
Requires-Dist: inquirer==3.4.0
Requires-Dist: markdown-it-py==3.0.0
Requires-Dist: mdurl==0.1.2
Requires-Dist: multidict==6.4.4
Requires-Dist: propcache==0.3.1
Requires-Dist: pyasn1==0.6.1
Requires-Dist: pyasn1_modules==0.4.2
Requires-Dist: pydantic==2.11.5
Requires-Dist: pydantic_core==2.33.2
Requires-Dist: Pygments==2.19.1
Requires-Dist: readchar==4.2.1
Requires-Dist: requests==2.32.3
Requires-Dist: rich==14.0.0
Requires-Dist: rsa==4.9.1
Requires-Dist: runs==1.2.2
Requires-Dist: sniffio==1.3.1
Requires-Dist: termcolor==2.3.0
Requires-Dist: typing-inspection==0.4.1
Requires-Dist: typing_extensions==4.14.0
Requires-Dist: urllib3==2.4.0
Requires-Dist: wcwidth==0.2.13
Requires-Dist: websockets==15.0.1
Requires-Dist: xmod==1.8.1
Requires-Dist: yarl==1.20.0
Requires-Dist: yaspin==3.1.0
Dynamic: author
Dynamic: author-email
Dynamic: classifier
Dynamic: description
Dynamic: description-content-type
Dynamic: home-page
Dynamic: license
Dynamic: license-file
Dynamic: requires-dist
Dynamic: requires-python
Dynamic: summary
